netunicorn/executor/__init__.py
netunicorn/executor/__main__.py
netunicorn/executor/executor.py
netunicorn/executor/utils.py
netunicorn_executor-0.4.2.dist-info/METADATA
netunicorn_executor-0.4.2.dist-info/WHEEL
netunicorn_executor-0.4.2.dist-info/top_level.txt
netunicorn_executor-0.4.2.dist-info/RECORD
