Metadata-Version: 2.1
Name: netunicorn-executor
Version: 0.4.2
Summary: netunicorn executor module
Author-email: Roman Beltiukov <rbeltiukov@ucsb.edu>
License: MIT
Keywords: netunicorn
Classifier: Programming Language :: Python :: 3
Classifier: Programming Language :: Python :: 3.9
Classifier: Programming Language :: Python :: 3.10
Classifier: Programming Language :: Python :: 3.11
Classifier: Programming Language :: Python :: 3.12
Requires-Python: >=3.9
Requires-Dist: cloudpickle
Requires-Dist: requests
Requires-Dist: netunicorn-base <0.5.0,>=0.4.0
